pulpcore/__init__.py
pulpcore/client/__init__.py
pulpcore/client/pulp_certguard/__init__.py
pulpcore/client/pulp_certguard/api_client.py
pulpcore/client/pulp_certguard/api_response.py
pulpcore/client/pulp_certguard/configuration.py
pulpcore/client/pulp_certguard/exceptions.py
pulpcore/client/pulp_certguard/py.typed
pulpcore/client/pulp_certguard/rest.py
pulpcore/client/pulp_certguard/api/__init__.py
pulpcore/client/pulp_certguard/api/contentguards_rhsm_api.py
pulpcore/client/pulp_certguard/api/contentguards_x509_api.py
pulpcore/client/pulp_certguard/models/__init__.py
pulpcore/client/pulp_certguard/models/certguard_rhsm_cert_guard.py
pulpcore/client/pulp_certguard/models/certguard_rhsm_cert_guard_response.py
pulpcore/client/pulp_certguard/models/certguard_x509_cert_guard.py
pulpcore/client/pulp_certguard/models/certguard_x509_cert_guard_response.py
pulpcore/client/pulp_certguard/models/paginatedcertguard_rhsm_cert_guard_response_list.py
pulpcore/client/pulp_certguard/models/paginatedcertguard_x509_cert_guard_response_list.py
pulpcore/client/pulp_certguard/models/patchedcertguard_rhsm_cert_guard.py
pulpcore/client/pulp_certguard/models/patchedcertguard_x509_cert_guard.py
pulp_certguard_client-3.101.0.dist-info/METADATA
pulp_certguard_client-3.101.0.dist-info/WHEEL
pulp_certguard_client-3.101.0.dist-info/top_level.txt
pulp_certguard_client-3.101.0.dist-info/RECORD
